{"cameraMode":{"drawMode":0,"name":"Shaded","section":"Shading Mode"},"sceneLighting":true,"audioPlay":false,"sceneViewState":{"showFog":true,"showMaterialUpdate":false,"showSkybox":true,"showFlares":true,"showImageEffects":true,"showParticleSystems":true},"in2DMode":false,"pivot":{"x":4.049875259399414,"y":2.4238033294677736,"z":5.793679237365723},"rotation":{"x":0.4794953763484955,"y":0.05915236473083496,"z":-0.0324031300842762,"w":0.8749819993972778},"size":22.896137237548829,"orthographic":false}